{
    "Sex": [
        "female",
        "male"
    ],
    "Embarked": [
        "C",
        "Q",
        "S"
    ],
    "Title": [
        "Master",
        "Miss",
        "Mr",
        "Mrs",
        "Rare"
    ],
    "TicketPrefix": [
        "A",
        "C",
        "CA",
        "NONE",
        "OTHER",
        "PC",
        "S",
        "SC",
        "SOTON",
        "STON",
        "W"
    ],
    "CabinDeck": [
        "A",
        "B",
        "C",
        "D",
        "E",
        "F",
        "G",
        "T",
        "Unknown"
    ],
    "AgeBand": [
        "(0.419, 20.0]",
        "(20.0, 25.0]",
        "(25.0, 30.0]",
        "(30.0, 40.0]",
        "(40.0, 80.0]"
    ],
    "FareBand": [
        "(-0.001, 7.854]",
        "(10.5, 21.679]",
        "(21.679, 39.688]",
        "(39.688, 512.329]",
        "(7.854, 10.5]"
    ],
    "Sex_Pclass": [
        "female_1",
        "female_2",
        "female_3",
        "male_1",
        "male_2",
        "male_3"
    ],
    "Sex_AgeBand": [
        "female_(0.419, 20.0]",
        "female_(20.0, 25.0]",
        "female_(25.0, 30.0]",
        "female_(30.0, 40.0]",
        "female_(40.0, 80.0]",
        "male_(0.419, 20.0]",
        "male_(20.0, 25.0]",
        "male_(25.0, 30.0]",
        "male_(30.0, 40.0]",
        "male_(40.0, 80.0]"
    ],
    "Embarked_Pclass": [
        "C_1",
        "C_2",
        "C_3",
        "Q_1",
        "Q_2",
        "Q_3",
        "S_1",
        "S_2",
        "S_3"
    ],
    "Title_AgeBand": [
        "Master_(0.419, 20.0]",
        "Master_(20.0, 25.0]",
        "Miss_(0.419, 20.0]",
        "Miss_(20.0, 25.0]",
        "Miss_(25.0, 30.0]",
        "Miss_(30.0, 40.0]",
        "Miss_(40.0, 80.0]",
        "Mr_(0.419, 20.0]",
        "Mr_(20.0, 25.0]",
        "Mr_(25.0, 30.0]",
        "Mr_(30.0, 40.0]",
        "Mr_(40.0, 80.0]",
        "Mrs_(0.419, 20.0]",
        "Mrs_(20.0, 25.0]",
        "Mrs_(25.0, 30.0]",
        "Mrs_(30.0, 40.0]",
        "Mrs_(40.0, 80.0]",
        "Rare_(20.0, 25.0]",
        "Rare_(25.0, 30.0]",
        "Rare_(30.0, 40.0]",
        "Rare_(40.0, 80.0]"
    ],
    "Pclass_FareBand": [
        "1_(-0.001, 7.854]",
        "1_(21.679, 39.688]",
        "1_(39.688, 512.329]",
        "2_(-0.001, 7.854]",
        "2_(10.5, 21.679]",
        "2_(21.679, 39.688]",
        "2_(39.688, 512.329]",
        "2_(7.854, 10.5]",
        "3_(-0.001, 7.854]",
        "3_(10.5, 21.679]",
        "3_(21.679, 39.688]",
        "3_(39.688, 512.329]",
        "3_(7.854, 10.5]"
    ]
}